examples/caching_bm25.py
examples/indexer_splade.py
examples/retriever_bm25.py
examples/scorer_monot5.py
pyterrier_caching/__init__.py
pyterrier_caching/indexer_cache.py
pyterrier_caching/key_value_cache.py
pyterrier_caching/retriever_cache.py
pyterrier_caching/scorer_cache.py
pyterrier_caching/util.py
pyterrier_caching/pt_docs/extras.rst
pyterrier_caching/pt_docs/index.rst
pyterrier_caching/pt_docs/indexer-cache.rst
pyterrier_caching/pt_docs/retriever-cache.rst
pyterrier_caching/pt_docs/scorer-cache.rst
pyterrier_caching-0.5.4.dist-info/licenses/LICENSE
pyterrier_caching-0.5.4.dist-info/METADATA
pyterrier_caching-0.5.4.dist-info/WHEEL
pyterrier_caching-0.5.4.dist-info/entry_points.txt
pyterrier_caching-0.5.4.dist-info/top_level.txt
pyterrier_caching-0.5.4.dist-info/RECORD
